{
  "date": "2026-06-13",
  "events": {
    "notification_receive": {
      "count": 583432,
      "users": 566007
    },
    "notification_dismiss": {
      "count": 228520,
      "users": 211696
    },
    "screen_view": {
      "count": 167508,
      "users": 43498
    },
    "user_engagement": {
      "count": 149825,
      "users": 39606
    },
    "session_start": {
      "count": 54452,
      "users": 46559
    },
    "mis_cupones": {
      "count": 26862,
      "users": 18065
    },
    "cupon_sn_qr_activacion": {
      "count": 16154,
      "users": 4490
    },
    "re_escaner_precios": {
      "count": 12776,
      "users": 2593
    },
    "notification_open": {
      "count": 9771,
      "users": 9375
    },
    "view_item_list": {
      "count": 9719,
      "users": 2589
    },
    "add_to_cart": {
      "count": 9020,
      "users": 1087
    },
    "search": {
      "count": 8281,
      "users": 2252
    },
    "switch_to_ecommerce": {
      "count": 7370,
      "users": 4471
    },
    "escaner_precios": {
      "count": 7069,
      "users": 4871
    },
    "favorito_mes_renovar": {
      "count": 5087,
      "users": 4499
    },
    "calculadora_agregar_producto": {
      "count": 4728,
      "users": 319
    },
    "view_cart": {
      "count": 4716,
      "users": 1075
    },
    "(other)": {
      "count": 4595,
      "users": 4262
    },
    "filter_cupones": {
      "count": 4014,
      "users": 2645
    },
    "favorito_semanal_activacion": {
      "count": 3578,
      "users": 3513
    },
    "listado_notificaciones": {
      "count": 3419,
      "users": 2255
    },
    "folletos": {
      "count": 3194,
      "users": 2389
    },
    "view_item": {
      "count": 2731,
      "users": 1034
    },
    "remove_from_cart": {
      "count": 2638,
      "users": 625
    },
    "select_item": {
      "count": 2614,
      "users": 986
    },
    "calculadora_home": {
      "count": 2575,
      "users": 1824
    },
    "view_promotion": {
      "count": 2363,
      "users": 1793
    },
    "inicio_registro": {
      "count": 2313,
      "users": 1197
    },
    "first_open": {
      "count": 2044,
      "users": 2043
    },
    "listado_notificaciones_click": {
      "count": 2035,
      "users": 1244
    },
    "tickets_compra": {
      "count": 1932,
      "users": 1616
    },
    "app_update": {
      "count": 1616,
      "users": 1610
    },
    "os_update": {
      "count": 1544,
      "users": 1543
    },
    "mi_perfil": {
      "count": 1489,
      "users": 1018
    },
    "favorito_semanal_volver_a_elegir": {
      "count": 1409,
      "users": 1312
    },
    "chat_bot": {
      "count": 1393,
      "users": 1011
    },
    "promociones": {
      "count": 1359,
      "users": 1145
    },
    "favorito_mes": {
      "count": 1261,
      "users": 947
    },
    "switch_to_sucursales": {
      "count": 1225,
      "users": 747
    },
    "app_remove": {
      "count": 1191,
      "users": 1113
    },
    "home_ahorros": {
      "count": 1027,
      "users": 956
    },
    "favorito_mes_nuevo": {
      "count": 868,
      "users": 754
    },
    "lista_compras": {
      "count": 852,
      "users": 668
    },
    "notification_foreground": {
      "count": 842,
      "users": 831
    },
    "add_shipping_info": {
      "count": 732,
      "users": 330
    },
    "ahorros_tips": {
      "count": 695,
      "users": 187
    },
    "scanner_maxi_branch_list": {
      "count": 468,
      "users": 297
    },
    "tarjeta_mi_carrefour": {
      "count": 415,
      "users": 343
    },
    "cerrar_sesion": {
      "count": 271,
      "users": 153
    },
    "sucursales": {
      "count": 210,
      "users": 164
    },
    "ahorros_cambio_mes": {
      "count": 180,
      "users": 35
    },
    "add_to_wishlist": {
      "count": 179,
      "users": 39
    },
    "buscar_precio_ean": {
      "count": 175,
      "users": 56
    },
    "ahorros_analisis": {
      "count": 141,
      "users": 129
    },
    "purchase": {
      "count": 117,
      "users": 114
    },
    "select_promotion": {
      "count": 76,
      "users": 54
    },
    "filter_escaner": {
      "count": 49,
      "users": 23
    },
    "favorito_semanal_favorito": {
      "count": 37,
      "users": 16
    },
    "consultas": {
      "count": 24,
      "users": 20
    },
    "app_exception": {
      "count": 21,
      "users": 17
    },
    "preguntas_frecuentes": {
      "count": 21,
      "users": 18
    },
    "terminos_y_condiciones": {
      "count": 8,
      "users": 8
    },
    "app_clear_data": {
      "count": 4,
      "users": 4
    },
    "dynamic_link_first_open": {
      "count": 2,
      "users": 2
    },
    "consultas_app": {
      "count": 1,
      "users": 1
    },
    "consultas_bsf": {
      "count": 1,
      "users": 1
    },
    "consultas_carrefour": {
      "count": 1,
      "users": 1
    },
    "(not set)": {
      "count": 0,
      "users": 85
    }
  }
}