{
  "date": "2026-06-20",
  "events": {
    "screen_view": {
      "count": 483,
      "users": 139
    },
    "user_engagement": {
      "count": 367,
      "users": 114
    },
    "session_start": {
      "count": 155,
      "users": 155
    },
    "cupon_sn_qr_activacion": {
      "count": 96,
      "users": 8
    },
    "view_item_list": {
      "count": 61,
      "users": 20
    },
    "add_to_cart": {
      "count": 59,
      "users": 11
    },
    "mis_cupones": {
      "count": 46,
      "users": 41
    },
    "switch_to_ecommerce": {
      "count": 45,
      "users": 23
    },
    "search": {
      "count": 44,
      "users": 13
    },
    "view_cart": {
      "count": 42,
      "users": 11
    },
    "notification_dismiss": {
      "count": 41,
      "users": 29
    },
    "switch_to_sucursales": {
      "count": 25,
      "users": 4
    },
    "remove_from_cart": {
      "count": 20,
      "users": 9
    },
    "first_open": {
      "count": 14,
      "users": 14
    },
    "select_item": {
      "count": 14,
      "users": 9
    },
    "notification_receive": {
      "count": 11,
      "users": 11
    },
    "view_item": {
      "count": 11,
      "users": 8
    },
    "mi_perfil": {
      "count": 10,
      "users": 7
    },
    "calculadora_agregar_producto": {
      "count": 9,
      "users": 1
    },
    "favorito_mes_renovar": {
      "count": 9,
      "users": 8
    },
    "app_remove": {
      "count": 8,
      "users": 8
    },
    "folletos": {
      "count": 7,
      "users": 5
    },
    "inicio_registro": {
      "count": 7,
      "users": 7
    },
    "promociones": {
      "count": 7,
      "users": 5
    },
    "escaner_precios": {
      "count": 6,
      "users": 5
    },
    "home_ahorros": {
      "count": 6,
      "users": 3
    },
    "ahorros_tips": {
      "count": 5,
      "users": 1
    },
    "calculadora_home": {
      "count": 5,
      "users": 5
    },
    "filter_cupones": {
      "count": 5,
      "users": 3
    },
    "app_update": {
      "count": 4,
      "users": 4
    },
    "chat_bot": {
      "count": 4,
      "users": 2
    },
    "os_update": {
      "count": 4,
      "users": 4
    },
    "tarjeta_mi_carrefour": {
      "count": 4,
      "users": 4
    },
    "add_shipping_info": {
      "count": 3,
      "users": 3
    },
    "favorito_mes": {
      "count": 3,
      "users": 3
    },
    "favorito_semanal_activacion": {
      "count": 3,
      "users": 3
    },
    "notification_open": {
      "count": 3,
      "users": 3
    },
    "tickets_compra": {
      "count": 3,
      "users": 3
    },
    "favorito_mes_nuevo": {
      "count": 2,
      "users": 2
    },
    "view_promotion": {
      "count": 2,
      "users": 2
    },
    "app_exception": {
      "count": 1,
      "users": 1
    },
    "favorito_semanal_volver_a_elegir": {
      "count": 1,
      "users": 1
    },
    "filter_escaner": {
      "count": 1,
      "users": 1
    },
    "lista_compras": {
      "count": 1,
      "users": 1
    },
    "listado_notificaciones": {
      "count": 1,
      "users": 1
    },
    "purchase": {
      "count": 1,
      "users": 1
    },
    "sucursales": {
      "count": 1,
      "users": 1
    },
    "(not set)": {
      "count": 0,
      "users": 8
    }
  }
}