{
  "date": "2026-06-13",
  "total_ecomm_orders": 2987,
  "total_ecomm_gmv": 0,
  "app": {
    "total": 608,
    "gmv": 59804816,
    "con_utm": 418,
    "sin_utm": 190,
    "segments": {
      "food": {
        "orders": 531,
        "gmv": 50916821
      },
      "non_food": {
        "orders": 3,
        "gmv": 4584880
      },
      "marketplace": {
        "orders": 2,
        "gmv": 665180
      },
      "quickcommerce": {
        "orders": 72,
        "gmv": 3637935
      }
    }
  },
  "participation_pct": 20.4,
  "utm_pct_sin": 31.3
}