{
  "date": "2026-05-23",
  "total_ecomm_orders": 2914,
  "total_ecomm_gmv": 0,
  "app": {
    "total": 541,
    "gmv": 44524061,
    "con_utm": 343,
    "sin_utm": 198,
    "segments": {
      "food": {
        "orders": 453,
        "gmv": 39767293
      },
      "non_food": {
        "orders": 3,
        "gmv": 878189
      },
      "marketplace": {
        "orders": 0,
        "gmv": 0
      },
      "quickcommerce": {
        "orders": 85,
        "gmv": 3878580
      }
    }
  },
  "participation_pct": 18.6,
  "utm_pct_sin": 36.6
}