[{"order_id":"1638468815339-01","fecha":"10/6/2026, 02:52:18","estado":"payment-approved","total":173743,"utm_source":"app_ecomm","utm_medium":"webview","segment":"food","email":"juanpa.mgi@gmail.com-262401652182b.ct.vtex.com.br","utm_status":"CON UTM"},{"order_id":"1638468815336-01","fecha":"10/6/2026, 02:48:01","estado":"payment-approved","total":80388,"utm_source":"app_ecomm","utm_medium":"webview","segment":"food","email":"oscarfofito@gmail.com-267601652751b.ct.vtex.com.br","utm_status":"CON UTM"},{"order_id":"1638468815335-01","fecha":"10/6/2026, 02:44:59","estado":"payment-approved","total":238291,"utm_source":"app_ecomm","utm_medium":"webview","segment":"food","email":"nahuel0697@gmail.com-264801652887b.ct.vtex.com.br","utm_status":"CON UTM"},{"order_id":"1638468815334-01","fecha":"10/6/2026, 02:44:19","estado":"payment-approved","total":129615,"utm_source":"app_ecomm","utm_medium":"webview","segment":"food","email":"silsantorsola@gmail.com-264301653632b.ct.vtex.com.br","utm_status":"CON UTM"},{"order_id":"1638468815332-01","fecha":"10/6/2026, 02:43:45","estado":"payment-approved","total":84352,"utm_source":"app_ecomm","utm_medium":"webview","segment":"food","email":"monona1970@gmail.com-267701653054b.ct.vtex.com.br","utm_status":"CON UTM"},{"order_id":"1638468815331-01","fecha":"10/6/2026, 02:39:56","estado":"payment-approved","total":173003,"utm_source":"app_ecomm","utm_medium":"webview","segment":"food","email":"alejandrafrodriguez54@gmail.com-266801651722b.ct.vtex.com.br","utm_status":"CON UTM"},{"order_id":"1638458815323-01","fecha":"10/6/2026, 02:17:20","estado":"payment-approved","total":71029,"utm_source":"app_ecomm","utm_medium":"webview","segment":"food","email":"jorgelinalizzi892@gmail.com-264901651195b.ct.vtex.com.br","utm_status":"CON UTM"},{"order_id":"1638458815322-01","fecha":"10/6/2026, 02:15:54","estado":"payment-approved","total":63500,"utm_source":"app_ecomm","utm_medium":"webview","segment":"food","email":"marcelacsofia@gmail.com-266401652603b.ct.vtex.com.br","utm_status":"CON UTM"},{"order_id":"1638448815267-01","fecha":"10/6/2026, 12:52:18","estado":"payment-approved","total":29970,"utm_source":"app_ecomm","utm_medium":"webview","segment":"food","email":"ricardopacheco@live.com.ar-261001651854b.ct.vtex.com.br","utm_status":"CON UTM"},{"order_id":"1638448815266-01","fecha":"10/6/2026, 12:51:38","estado":"payment-approved","total":194525,"utm_source":"app_ecomm","utm_medium":"webview","segment":"food","email":"gbgadz@gmail.com-266301651463b.ct.vtex.com.br","utm_status":"CON UTM"},{"order_id":"1638448815258-01","fecha":"10/6/2026, 12:42:18","estado":"payment-approved","total":71691,"utm_source":"","utm_medium":"","segment":"food","email":"yamileze_b@hotmail.com-265501651054b.ct.vtex.com.br","utm_status":"SIN UTM"},{"order_id":"1638448815255-01","fecha":"10/6/2026, 12:40:51","estado":"invoiced","total":135830,"utm_source":"app_ecomm","utm_medium":"webview","segment":"non_food","email":"rocio291091@gmail.com-260301650339b.ct.vtex.com.br","utm_status":"CON UTM"},{"order_id":"1638448815245-01","fecha":"10/6/2026, 12:35:29","estado":"payment-approved","total":29173,"utm_source":"app_ecomm","utm_medium":"webview","segment":"food","email":"mmariakinsfater@gmail.com-263901650101b.ct.vtex.com.br","utm_status":"CON UTM"},{"order_id":"1638458815306-01","fecha":"10/6/2026, 01:39:39","estado":"payment-approved","total":23704,"utm_source":"app_ecomm","utm_medium":"webview","segment":"food","email":"cnm_90@yahoo.com.ar-266401652526b.ct.vtex.com.br","utm_status":"CON UTM"},{"order_id":"1638448815292-01","fecha":"10/6/2026, 01:27:06","estado":"payment-approved","total":25624,"utm_source":"app_ecomm","utm_medium":"webview","segment":"food","email":"pamelafdez195@gmail.com-266301651562b.ct.vtex.com.br","utm_status":"CON UTM"},{"order_id":"1638448815286-01","fecha":"10/6/2026, 01:22:46","estado":"payment-approved","total":53823,"utm_source":"app_ecomm","utm_medium":"webview","segment":"food","email":"villavicencio.gasargentino@hotmail.com-262001650763b.ct.vtex.com.br","utm_status":"CON UTM"},{"order_id":"1638448815281-01","fecha":"10/6/2026, 01:16:00","estado":"payment-approved","total":39765,"utm_source":"app_ecomm","utm_medium":"webview","segment":"food","email":"jorgelinalizzi892@gmail.com-267701652840b.ct.vtex.com.br","utm_status":"CON UTM"},{"order_id":"1638438815231-01","fecha":"10/6/2026, 12:22:29","estado":"payment-approved","total":414613,"utm_source":"app_ecomm","utm_medium":"webview","segment":"food","email":"vcalabria@uhsnetwork.net-262401651790b.ct.vtex.com.br","utm_status":"CON UTM"},{"order_id":"1638438815204-01","fecha":"10/6/2026, 12:09:13","estado":"payment-approved","total":49307,"utm_source":"app_ecomm","utm_medium":"webview","segment":"food","email":"santinomolinasvarre@gmail.com-261401650444b.ct.vtex.com.br","utm_status":"CON UTM"},{"order_id":"1638438815200-01","fecha":"10/6/2026, 12:07:30","estado":"payment-approved","total":50610,"utm_source":"app_ecomm","utm_medium":"webview","segment":"food","email":"aylentejerizo@gmail.com-268801652624b.ct.vtex.com.br","utm_status":"CON UTM"},{"order_id":"1638438815193-01","fecha":"10/6/2026, 12:04:33","estado":"payment-approved","total":17473,"utm_source":"app_ecomm","utm_medium":"webview","segment":"food","email":"villordosylvina@gmail.com-264401650430b.ct.vtex.com.br","utm_status":"CON UTM"},{"order_id":"1638438815180-01","fecha":"10/6/2026, 12:00:46","estado":"payment-approved","total":145687,"utm_source":"app_ecomm","utm_medium":"webview","segment":"food","email":"escobarvictoriaok@gmail.com-264701652916b.ct.vtex.com.br","utm_status":"CON UTM"}]